fast_lzss.cpython-37m-darwin.so
tbxi/__init__.py
tbxi/__main__.py
tbxi/binescape.py
tbxi/binhex.py
tbxi/bootinfo_build.py
tbxi/bootinfo_dump.py
tbxi/cfrg_rsrc.py
tbxi/dispatcher.py
tbxi/fast_lzss.cpython-37m-darwin.so
tbxi/lowlevel.py
tbxi/lzss.py
tbxi/namedtuplestruct.py
tbxi/ndrv_name_suggest.py
tbxi/parcel_dump.py
tbxi/parcels_build.py
tbxi/parcels_dump.py
tbxi/pef.py
tbxi/pef_info.py
tbxi/powerpc_build.py
tbxi/powerpc_dump.py
tbxi/prclc.py
tbxi/prcldump.py
tbxi/romdump.py
tbxi/slow_lzss.py
tbxi/stringstruct.py
tbxi/supermario_build.py
tbxi/supermario_dump.py
tbxi-0.12.dist-info/LICENSE
tbxi-0.12.dist-info/METADATA
tbxi-0.12.dist-info/WHEEL
tbxi-0.12.dist-info/entry_points.txt
tbxi-0.12.dist-info/top_level.txt
tbxi-0.12.dist-info/zip-safe
tbxi-0.12.dist-info/RECORD
