Metadata-Version: 2.1
Name: tbxi
Version: 0.12
Summary: Tools to compile and inspect Macintosh ROM images
Home-page: https://github.com/elliotnunn/tbxi
Author: Elliot Nunn
Author-email: elliotnunn@fastmail.com
License: UNKNOWN
Platform: UNKNOWN
Classifier: Programming Language :: Python :: 3 :: Only
Classifier: Programming Language :: C
Classifier: Operating System :: OS Independent
Classifier: Intended Audience :: Developers
Classifier: Topic :: Software Development :: Build Tools
Classifier: License :: OSI Approved :: MIT License
Requires-Dist: macresources
